README
setup.py
sequin/__init__.py
sequin/base.py
sequin/errors.py
sequin.egg-info/PKG-INFO
sequin.egg-info/SOURCES.txt
sequin.egg-info/dependency_links.txt
sequin.egg-info/not-zip-safe
sequin.egg-info/top_level.txt