Metadata-Version: 1.0
Name: sequin
Version: 0.0.1
Summary: Sequin: Event Sourcing Framework for Python
Home-page: https://github.com/josefdlange/sequin
Author: Josef Lange
Author-email: josef.d.lange@me.com
License: MIT
Platform: UNKNOWN
